{
  "task_id": "task_default",
  "turn_id": 25,
  "new_nodes": [
    {
      "node_id": "n_0082",
      "type": "Fact",
      "content": "P0烟测A和B均通过：烟测A中智能体正确读取skills/quant_assistant/SKILL.md和TOOLS.md并调用脚本查询实例；烟测B中智能体读取根TOOLS.md后未触发量化脚本，给出自然语言市场分析。新根TOOLS.md路由层和quant_assistant本地TOOLS.md已正常工作。",
      "entity_ref": null,
      "state": null,
      "priority": "should_include"
    }
  ],
  "updated_nodes": [
    {
      "node_id": "n_0080",
      "changes": {
        "state": "deployed"
      },
      "reason": "烟测A证实该文件已被智能体正确读取并用于指导脚本调用，说明已部署生效。"
    },
    {
      "node_id": "n_0081",
      "changes": {
        "state": "deployed"
      },
      "reason": "烟测B证实该文件已被智能体读取并成功分诊，未误触发量化脚本，说明已部署生效。"
    }
  ],
  "superseded_nodes": [],
  "new_edges": [
    {
      "source": "n_0082",
      "target": "n_0079",
      "relation": "derived_from"
    },
    {
      "source": "n_0082",
      "target": "n_0073",
      "relation": "supports"
    }
  ]
}
