{
  "ok": false,
  "summary": {
    "nodes": 110,
    "edges": 175,
    "active_nodes": 92,
    "active_edges": 175,
    "superseded_nodes": 18,
    "errors": 3,
    "warnings": 0
  },
  "adjudication_policy": {
    "current_membership_field": "status",
    "state_participates_in_current_membership": true,
    "state_gate_field": "state",
    "pending_state_rule": "exclude state=open pending open-task candidates from current membership",
    "active_status_value": "active",
    "superseded_status_value": "superseded"
  },
  "status_observations": {
    "superseded_node_ids": [
      "n_0010",
      "n_0012",
      "n_0014",
      "n_0027",
      "n_0030",
      "n_0033",
      "n_0034",
      "n_0049",
      "n_0052",
      "n_0055",
      "n_0056",
      "n_0059",
      "n_0074",
      "n_0090",
      "n_0092",
      "n_0094",
      "n_0095",
      "n_0107"
    ],
    "excluded_due_to_state_node_ids": []
  },
  "relation_enum": [
    "depends_on",
    "derived_from",
    "implements",
    "invalidates",
    "produces",
    "refines",
    "serves",
    "supersedes",
    "supports"
  ],
  "minimal_state_enum": [
    "blocked",
    "cancelled",
    "deployed",
    "implemented",
    "in_progress",
    "open",
    "resolved",
    "unknown"
  ],
  "errors": [
    {
      "level": "error",
      "code": "INVALIDATES_TARGET_NOT_SUPERSEDED",
      "message": "invalidates 边 edge[144] 指向的节点 n_0060 未标记为 superseded。",
      "edge_id": "edge[144]",
      "source": "n_0094",
      "target": "n_0060",
      "target_status": null,
      "target_active": null
    },
    {
      "level": "error",
      "code": "INVALIDATES_TARGET_NOT_SUPERSEDED",
      "message": "invalidates 边 edge[172] 指向的节点 n_0105 未标记为 superseded。",
      "edge_id": "edge[172]",
      "source": "n_0107",
      "target": "n_0105",
      "target_status": null,
      "target_active": null
    },
    {
      "level": "error",
      "code": "INVALIDATES_TARGET_NOT_SUPERSEDED",
      "message": "invalidates 边 edge[173] 指向的节点 n_0093 未标记为 superseded。",
      "edge_id": "edge[173]",
      "source": "n_0107",
      "target": "n_0093",
      "target_status": null,
      "target_active": null
    }
  ],
  "warnings": []
}